twat_mp/__init__.py
twat_mp/async_mp.py
twat_mp/mp.py
twat_mp-2.6.2.dist-info/METADATA
twat_mp-2.6.2.dist-info/WHEEL
twat_mp-2.6.2.dist-info/entry_points.txt
twat_mp-2.6.2.dist-info/licenses/LICENSE
twat_mp-2.6.2.dist-info/RECORD
