Metadata-Version: 2.4
Name: twat-mp
Version: 2.6.2
Summary: Parallel processing utilities using Pathos mpprocessing library
Project-URL: Documentation, https://github.com/twardoch/twat-mp#readme
Project-URL: Issues, https://github.com/twardoch/twat-mp/issues
Project-URL: Source, https://github.com/twardoch/twat-mp
Author-email: Adam Twardoch <adam+github@twardoch.com>
License-Expression: MIT
License-File: LICENSE
Keywords: map,mpprocessing,parallel,pathos,pool
Classifier: Development Status :: 4 - Beta
Classifier: Programming Language :: Python
Classifier: Programming Language :: Python :: 3.10
Classifier: Programming Language :: Python :: 3.11
Classifier: Programming Language :: Python :: 3.12
Classifier: Programming Language :: Python :: Implementation :: CPython
Classifier: Programming Language :: Python :: Implementation :: PyPy
Requires-Python: >=3.10
Requires-Dist: aiomultiprocess>=0.9.1
Requires-Dist: pathos>=0.3.3
Requires-Dist: twat>=1.8.1
Provides-Extra: all
Requires-Dist: aiomultiprocess>=0.9.1; extra == 'all'
Requires-Dist: pathos>=0.3.3; extra == 'all'
Requires-Dist: twat>=1.0.0; extra == 'all'
Provides-Extra: dev
Requires-Dist: pre-commit>=3.6.0; extra == 'dev'
Provides-Extra: test
Requires-Dist: matplotlib>=3.7.0; extra == 'test'
Requires-Dist: numpy>=1.24.0; extra == 'test'
Requires-Dist: pandas>=2.0.0; extra == 'test'
Requires-Dist: pytest-benchmark[histogram]>=4.0.0; extra == 'test'
Requires-Dist: pytest-cov>=4.0.0; extra == 'test'
Requires-Dist: pytest-xdist>=3.5.0; extra == 'test'
Requires-Dist: pytest>=7.0.0; extra == 'test'
